raindinners/__init__.py
raindinners/__meta__.py
raindinners/exceptions.py
raindinners/network.py
raindinners/raindinners.py
raindinners/session.py
raindinners/methods/__init__.py
raindinners/methods/base.py
raindinners/methods/get_bonus.py
raindinners/methods/get_me.py
raindinners/methods/get_user.py
raindinners/methods/sign_in.py
raindinners/methods/update_balance.py
raindinners/types/__init__.py
raindinners/types/authorization.py
raindinners/types/balance.py
raindinners/types/base.py
raindinners/types/user.py
raindinners/utils/__init__.py
raindinners/utils/authorization.py
raindinners/utils/pydantic.py
raindinners/utils/response_validator.py
raindinners-0.2.dist-info/METADATA
raindinners-0.2.dist-info/WHEEL
raindinners-0.2.dist-info/RECORD
